symbot/__init__.py
symbot/__main__.py
symbot/config.py
symbot/chat/__init__.py
symbot/chat/chat.py
symbot/chat/message.py
symbot/control/__init__.py
symbot/control/control.py
symbot/control/auxiliary/__init__.py
symbot/control/auxiliary/cooldowns.py
symbot/control/auxiliary/environment.py
symbot/control/auxiliary/permissions.py
symbot/control/auxiliary/settings.py
symbot/data/command_settings.json
symbot/data/environment.json
symbot/data/user_permissions.json
symbot/dev/__init__.py
symbot/dev/commands/__init__.py
symbot/dev/commands/_base_command.py
symbot/dev/commands/auto_responses/__init__.py
symbot/dev/commands/auto_responses/hey.py
symbot/dev/commands/counters/__init__.py
symbot/dev/commands/counters/bad.py
symbot/dev/commands/counters/good.py
symbot/dev/commands/counters/howbad.py
symbot/dev/commands/counters/well.py
symbot/dev/commands/info/__init__.py
symbot/dev/commands/info/commands.py
symbot/dev/commands/info/time.py
symbot/dev/commands/info/uptime.py
symbot/dev/commands/interactive/__init__.py
symbot/dev/commands/interactive/highfive.py
symbot/dev/commands/new/__init__.py
symbot/dev/commands/new/test.py
symbot/dev/media/__init__.py
symbot/dev/media/_base_media.py
symbot/dev/media/localtime.py
symbot/dev/media/uptime.py
symbot/dev/meta/__init__.py
symbot/dev/meta/_base_meta_command.py
symbot/dev/meta/_builder.py
symbot/dev/meta/command.py
symbot/dev/meta/purge.py
symbot/dev/meta/setcmdsetting.py
symbot/dev/meta/setuserperm.py
symbot/dev/meta/var.py
symbot/util/__init__.py
symbot/util/strings.py
symbot/util/updater.py
symbot-0.1.1.dist-info/LICENSE
symbot-0.1.1.dist-info/METADATA
symbot-0.1.1.dist-info/WHEEL
symbot-0.1.1.dist-info/top_level.txt
symbot-0.1.1.dist-info/RECORD
