Metadata-Version: 2.1
Name: symbot
Version: 0.1.1
Summary: A twitch chat bot for developers.
Home-page: https://github.com/tobi208/symbot
Author: Tobias Lass
Author-email: tobi208@github.com
License: UNKNOWN
Project-URL: Bug Tracker, https://github.com/tobi208/symbot/issues
Platform: UNKNOWN
Classifier: Programming Language :: Python :: 3
Classifier: License :: OSI Approved :: GNU General Public License v3 (GPLv3)
Classifier: Operating System :: OS Independent
Requires-Python: >=3.7
License-File: LICENSE
